Metadata-Version: 2.1
Name: aio2b2t
Version: 1.0
Summary: aio2b2t is a modern, async, API wrapper for https://2b2t.dev and https://2b2t.io.
Home-page: https://github.com/DontTreadOnGerman/aio2b2t
Author: DTOG
Author-email: arstotzkanlool@gmail.com
License: UNKNOWN
Platform: UNKNOWN
Classifier: Programming Language :: Python :: 3.6
Classifier: Programming Language :: Python :: 3.7
Classifier: Programming Language :: Python :: 3.8
Classifier: Programming Language :: Python :: 3.9
Classifier: License :: OSI Approved :: MIT License
Classifier: Operating System :: OS Independent
Requires-Python: >=3.6
